{
    "issue": {
        "title": "🌳 Discuss subtree building and crafting",
        "created_at": "2024-04-16T04:20:00Z",
        "updated_at": "2024-04-16T04:20:00Z",
        "content": [
            {
                "body": [
                    {
                        "type": "text",
                        "body": "Follow up issue: Answer open questions and check definition again."
                    },
                    {
                        "type": "itemize",
                        "caption": "Previous Issues:",
                        "body": [
                            "#4"
                        ]
                    }
                ]
            },
            {
                "title": "Open questions",
                "body": [
                    {
                        "type": "boxes",
                        "caption": "07.04, Tag Iteration A-Z:",
                        "body": [
                            "Should planning be reinstated as parent node?",
                            "Are blueprints related to space?",
                            "Is copypaste a blueprint (planning vs duplication)?",
                            "Contains copy paste planning?"
                        ]
                    },
                    {
                        "type": "boxes",
                        "caption": "15.04, Tree Iteration IV:",
                        "body": [
                            "Clarify _customizable_ and _preset_!",
                            "Clarify _exploit as blueprint_ (Banished)!"
                        ]
                    }
                ]
            }
        ],
        "labels": [
            "effort:medium",
            "priority:low"
        ],
        "milestone": 4
    },
    "comments": [
    ]
}
